ModelViewer/__init__.py
ModelViewer/_comm_api.py
ModelViewer/_demodata.py
ModelViewer/_plot_temporal_viewer.py
ModelViewer/build/temporalViewer.js
model_viewer-0.1.2.dist-info/METADATA
model_viewer-0.1.2.dist-info/WHEEL
model_viewer-0.1.2.dist-info/top_level.txt
model_viewer-0.1.2.dist-info/RECORD
