Metadata-Version: 2.1
Name: model-viewer
Version: 0.1.2
Summary: Model Viewer. Enables the exploration of temporal distribution of the model outputs in Jupyter Notebooks
Home-page: https://github.com/soniacq/TemporalViewer
Author: Sonia Castelo
Author-email: s.castelo@nyu.edu
License: UNKNOWN
Platform: UNKNOWN
Classifier: Programming Language :: Python :: 3
Classifier: License :: OSI Approved :: BSD License
Classifier: Operating System :: OS Independent
Requires-Python: >=3.6
